[{"dpi":3159824019880,"name":"Maurine Cordelet","username":"mcordelet0","password":"Ea7QiwN","phone":1898986129,"admin":true},
{"dpi":3524058476928,"name":"Moselle Browne","username":"mbrowne1","password":"6zfDyxS1j","phone":2804316541,"admin":false},
{"dpi":9092373023254,"name":"Carina Gainsborough","username":"cgainsborough2","password":"g2kC9ki9","phone":1491136148,"admin":false},
{"dpi":3286405685081,"name":"Maggie Mora","username":"mmora3","password":"4rcqvPjk","phone":4707254615,"admin":false},
{"dpi":5368507923549,"name":"Xymenes Zecchini","username":"xzecchini4","password":"EazN6U","phone":4424465037,"admin":false},
{"dpi":9926778599863,"name":"Dix Leere","username":"dleere5","password":"zSZ8TK","phone":1278518208,"admin":false},
{"dpi":6732455234280,"name":"Lizzy Wardingly","username":"lwardingly6","password":"wOGHCAcuDB","phone":3293775783,"admin":false},
{"dpi":6870217392712,"name":"Virgil Rye","username":"vrye7","password":"tSMAOX99Miw","phone":4192650378,"admin":false},
{"dpi":6234906187114,"name":"Darin Cresar","username":"dcresar8","password":"RbdZcbZky1u","phone":8043706001,"admin":true},
{"dpi":6272815859285,"name":"Jolynn Goody","username":"jgoody9","password":"8RBQ3QxVWu9","phone":4562924854,"admin":false},
{"dpi":7861424169231,"name":"Mattie Baulk","username":"mbaulka","password":"oCyKDWEPwb","phone":1334533066,"admin":false},
{"dpi":2193382136998,"name":"Bernadette Suttie","username":"bsuttieb","password":"8J9I1H9Gmuy","phone":6862748307,"admin":false},
{"dpi":8041711984564,"name":"Obediah Sondon","username":"osondonc","password":"DcNoc7Ym4nz1","phone":1637307754,"admin":false},
{"dpi":1359678728468,"name":"Dorian Fevers","username":"dfeversd","password":"zzYMjKpm","phone":6554095200,"admin":false},
{"dpi":5087867639844,"name":"Remy Annes","username":"rannese","password":"HbqdgSpKaG","phone":3068770215,"admin":false},
{"dpi":8825119444146,"name":"Tiebout Maffy","username":"tmaffyf","password":"cyiRb2TrH2i","phone":9408382344,"admin":true},
{"dpi":2213465602499,"name":"Lynna Aysh","username":"layshg","password":"nLl2brO","phone":7332992209,"admin":false},
{"dpi":8536141162719,"name":"Ailey Mowne","username":"amowneh","password":"OBZqSzsCdAKM","phone":4248460094,"admin":false},
{"dpi":2612718859499,"name":"Meara Ongin","username":"mongini","password":"BpXl2G","phone":9911702680,"admin":false},
{"dpi":9543404995216,"name":"Darrin Vasyatkin","username":"dvasyatkinj","password":"NmCxygWB5q9G","phone":5328406475,"admin":false},
{"dpi":3130412213844,"name":"Carissa Kemmish","username":"ckemmishk","password":"54tdAti","phone":7232241030,"admin":false},
{"dpi":2772699043899,"name":"Gibbie Conlon","username":"gconlonl","password":"9xDztsdftJ","phone":6959438098,"admin":false},
{"dpi":2327837478780,"name":"Steffie Madoc-Jones","username":"smadocjonesm","password":"VGPFw0BDBs","phone":6201709189,"admin":false},
{"dpi":9276459372821,"name":"Dulcinea Paybody","username":"dpaybodyn","password":"Lgguq9r9","phone":9672574224,"admin":false},
{"dpi":8274842015829,"name":"Burlie Iacovone","username":"biacovoneo","password":"qms2FRUI3Y46","phone":1806455185,"admin":false},
{"dpi":6497718189660,"name":"Vanna Scouller","username":"vscoullerp","password":"3mStsn2AD","phone":9455353675,"admin":false},
{"dpi":6562607034675,"name":"Naoma Ryley","username":"nryleyq","password":"Q9hHT8Idb8t","phone":1033692278,"admin":false},
{"dpi":5939267883183,"name":"Anthia Cuddon","username":"acuddonr","password":"ZawUeWcacRLZ","phone":3035867855,"admin":false},
{"dpi":6909324433929,"name":"Lauryn Collough","username":"lcolloughs","password":"7QDXTE","phone":5079544973,"admin":false},
{"dpi":5142838823504,"name":"Jemimah Carillo","username":"jcarillot","password":"ylF72Ev","phone":2807215127,"admin":false},
{"dpi":5613686535131,"name":"Jessey Fidgin","username":"jfidginu","password":"qZveGy0EQ","phone":7588788794,"admin":false},
{"dpi":1454035863387,"name":"Dodi Crews","username":"dcrewsv","password":"Ythb971h","phone":6533000249,"admin":false},
{"dpi":8158776585682,"name":"Way Eborn","username":"webornw","password":"39DLfVoqXi","phone":6673257745,"admin":false},
{"dpi":2524719857150,"name":"Alyse Casiroli","username":"acasirolix","password":"2yOjhvFuk","phone":1464352588,"admin":false},
{"dpi":2708878042875,"name":"Rhys Flohard","username":"rflohardy","password":"yjuwmWYX5","phone":5037498512,"admin":false},
{"dpi":4135905126580,"name":"Corina Mayes","username":"cmayesz","password":"BDt0p4","phone":6034808064,"admin":true},
{"dpi":9101451605340,"name":"Crissy Achromov","username":"cachromov10","password":"ANnzFxGKwE","phone":8167256663,"admin":false},
{"dpi":5759771332584,"name":"Reagan Marjot","username":"rmarjot11","password":"eykyVgbn","phone":7305513466,"admin":false},
{"dpi":6111641628761,"name":"Tades Bleibaum","username":"tbleibaum12","password":"RIhXH8m","phone":8532439506,"admin":false},
{"dpi":9158958053312,"name":"Uta Kirsz","username":"ukirsz13","password":"MPAuo2JdJD4","phone":5813376295,"admin":false},
{"dpi":4473611784109,"name":"Doris Byard","username":"dbyard14","password":"BC4mLcj","phone":2416786408,"admin":false},
{"dpi":9814261167310,"name":"Russ Rawe","username":"rrawe15","password":"Xh1eocAg","phone":8468677437,"admin":false},
{"dpi":2324753958178,"name":"Dixie Dulieu","username":"ddulieu16","password":"XyPttYQoK","phone":5877414184,"admin":false},
{"dpi":4641445953294,"name":"Andriette Churchard","username":"achurchard17","password":"wJgcDhuP6st","phone":8849313619,"admin":false},
{"dpi":3804266970170,"name":"Lyssa McLarens","username":"lmclarens18","password":"YdXBPFQW9AkL","phone":3114319226,"admin":false},
{"dpi":6895031025066,"name":"Kiri McCaghan","username":"kmccaghan19","password":"l1DEsi6PzH","phone":1722526337,"admin":false},
{"dpi":9062496980146,"name":"Mariele Streets","username":"mstreets1a","password":"xafRWoi","phone":7686896715,"admin":false},
{"dpi":9567157369332,"name":"Jill Surgeoner","username":"jsurgeoner1b","password":"UZF6DO","phone":8826006354,"admin":false},
{"dpi":1584394532557,"name":"Margarita Jammet","username":"mjammet1c","password":"CwWVmlQPZ","phone":5988859667,"admin":false},
{"dpi":8436879875427,"name":"Massimo Calderonello","username":"mcalderonello1d","password":"whj6IZw0e","phone":8619137089,"admin":false},
{"dpi":9932038793363,"name":"Lelia Eaddy","username":"leaddy1e","password":"y93nUc4efQC","phone":9203218555,"admin":false},
{"dpi":2559483098596,"name":"Caye Sporrij","username":"csporrij1f","password":"f9tgzhA","phone":3284762709,"admin":false},
{"dpi":6442957551014,"name":"Catina Dietz","username":"cdietz1g","password":"boxXeemWO","phone":6997104834,"admin":false},
{"dpi":5283184547244,"name":"Christopher Lode","username":"clode1h","password":"uzFgtUY","phone":7235772922,"admin":false},
{"dpi":4515089364554,"name":"Dickie Theaker","username":"dtheaker1i","password":"1nsGLlUqhKs","phone":5102554479,"admin":false},
{"dpi":5862627930619,"name":"Cullan Humpherson","username":"chumpherson1j","password":"hxrpu1","phone":4613726349,"admin":false},
{"dpi":2337249191661,"name":"Thomas Pietzke","username":"tpietzke1k","password":"BZSxb28J7","phone":6218394852,"admin":false},
{"dpi":2209103358108,"name":"Dalston Jarrett","username":"djarrett1l","password":"kLZH5p1F363p","phone":4318418438,"admin":false},
{"dpi":4347151300189,"name":"Mariel Kidwell","username":"mkidwell1m","password":"Bcrm5D","phone":7429434365,"admin":true},
{"dpi":9051333843258,"name":"Martina Welford","username":"mwelford1n","password":"afJuh8EIyD","phone":4377217492,"admin":false},
{"dpi":6223388518773,"name":"Brnaba Greenalf","username":"bgreenalf1o","password":"WXEkchA4aiVD","phone":7431212772,"admin":false},
{"dpi":5985871194899,"name":"Hanan Rowantree","username":"hrowantree1p","password":"FyNseWzVq","phone":5872516216,"admin":false},
{"dpi":5760252311742,"name":"Hall Judkin","username":"hjudkin1q","password":"d5yC9KjrO78b","phone":5413817401,"admin":false},
{"dpi":2747056587012,"name":"Arel Antognazzi","username":"aantognazzi1r","password":"PtCgFGyFD","phone":1604518121,"admin":false},
{"dpi":2864296822847,"name":"Agnes Preator","username":"apreator1s","password":"XJGn1em8","phone":5153677179,"admin":false},
{"dpi":1938445001039,"name":"Garrik Gorrissen","username":"ggorrissen1t","password":"2yzxQSSaJ","phone":9462343643,"admin":false},
{"dpi":7231048601128,"name":"Flem Marc","username":"fmarc1u","password":"CWkdgqxF","phone":8976146142,"admin":false},
{"dpi":8935588569206,"name":"Pippa Faucett","username":"pfaucett1v","password":"vVijigzTk","phone":6573568695,"admin":false},
{"dpi":3743968579549,"name":"Tracie Rainbird","username":"trainbird1w","password":"XGkkDLc","phone":3331768414,"admin":false},
{"dpi":1319730029004,"name":"Biddy Letten","username":"bletten1x","password":"z6tMOfv02bo","phone":1854987141,"admin":false},
{"dpi":6656095415018,"name":"Gaylord Wilprecht","username":"gwilprecht1y","password":"FcbkVAwdE","phone":4516783682,"admin":false},
{"dpi":6106135417137,"name":"Margi Terzo","username":"mterzo1z","password":"zqRA09vP1Pzt","phone":4442243471,"admin":false},
{"dpi":9584148891172,"name":"Fredric Verrillo","username":"fverrillo20","password":"yIURKzpQQHc4","phone":6355567623,"admin":false},
{"dpi":8553225574328,"name":"Wyatt Fairebrother","username":"wfairebrother21","password":"5mruR4wUuiI","phone":2114728097,"admin":false},
{"dpi":4385693694746,"name":"Rriocard Cormack","username":"rcormack22","password":"dab1fhTMU","phone":4276422500,"admin":false},
{"dpi":5278926619847,"name":"Milena Limpenny","username":"mlimpenny23","password":"sDUeF81X42","phone":7917753362,"admin":false},
{"dpi":3210895164446,"name":"Townie Boyse","username":"tboyse24","password":"OcQhwrK","phone":5311188090,"admin":false},
{"dpi":1181523328319,"name":"Jeane Cawsy","username":"jcawsy25","password":"mf182HRn","phone":2749618017,"admin":false},
{"dpi":7251826650969,"name":"Almeta Haythorn","username":"ahaythorn26","password":"B5fmjFE","phone":9054067366,"admin":false},
{"dpi":1295948696371,"name":"Lauritz de la Valette Parisot","username":"lde27","password":"TNZRdtf","phone":8169781106,"admin":false},
{"dpi":4375610766985,"name":"Cirstoforo Fenich","username":"cfenich28","password":"N39SRCdQBMk0","phone":6032185337,"admin":false},
{"dpi":8559560440470,"name":"Raye Delouch","username":"rdelouch29","password":"Wi7WBWWd2jN","phone":2022701972,"admin":false},
{"dpi":8392700319972,"name":"Grady Bythway","username":"gbythway2a","password":"L1mYeUMOxix1","phone":4695471992,"admin":false},
{"dpi":1527659207897,"name":"Tildy Boot","username":"tboot2b","password":"yuqmEsP3HY1B","phone":1605974741,"admin":false},
{"dpi":5140203141242,"name":"Holmes Chace","username":"hchace2c","password":"AKty6C2oxp5P","phone":2388937173,"admin":false},
{"dpi":7468190502007,"name":"Jarvis Comini","username":"jcomini2d","password":"dS992jw37L8B","phone":9163149070,"admin":false},
{"dpi":9836435673124,"name":"Helenka Tamburi","username":"htamburi2e","password":"kIKEEnOQSv","phone":1606584943,"admin":false},
{"dpi":1108557739309,"name":"Selene Flexman","username":"sflexman2f","password":"ne3gP06QBFI","phone":3546484776,"admin":false},
{"dpi":9886771325920,"name":"Ajay Giffin","username":"agiffin2g","password":"UR6HEX9aP","phone":2247073050,"admin":false},
{"dpi":2322918158594,"name":"Ingmar Bischop","username":"ibischop2h","password":"JHHq1l","phone":2979533841,"admin":false},
{"dpi":2243152212800,"name":"Karol Yearsley","username":"kyearsley2i","password":"XbgAYO","phone":1811145819,"admin":false},
{"dpi":4785416409225,"name":"Kenn Witherup","username":"kwitherup2j","password":"32NTsJDEXSz2","phone":3287235923,"admin":false},
{"dpi":6652198444022,"name":"Rutger Casellas","username":"rcasellas2k","password":"ukAawKTa78","phone":1022418678,"admin":false},
{"dpi":3285768280557,"name":"Raffarty Flewin","username":"rflewin2l","password":"l5xIIG","phone":9995508079,"admin":false},
{"dpi":5087287956953,"name":"Wilmer Draisey","username":"wdraisey2m","password":"ZgmhWj","phone":4162711935,"admin":false},
{"dpi":8688695150456,"name":"Ewen Delamar","username":"edelamar2n","password":"X7Xx0ylSGiA","phone":2886483463,"admin":false},
{"dpi":1434819490090,"name":"Arvy Workes","username":"aworkes2o","password":"UXtbE8OWK","phone":1566422186,"admin":false},
{"dpi":8698960355047,"name":"Tris Panting","username":"tpanting2p","password":"AkrOTCi3q","phone":7347664054,"admin":false},
{"dpi":3149550971067,"name":"Kareem Ghilks","username":"kghilks2q","password":"ADAYYg","phone":5195761473,"admin":false},
{"dpi":2486502685697,"name":"Babara Edmed","username":"bedmed2r","password":"OGjtIucus2L","phone":6413231178,"admin":false}]